Metadata-Version: 2.1
Name: desktoppython
Version: 0.1
Summary: Basic data analysis with Python
Home-page: https://github.com/Shinnoyaninsha/desktoppython
Download-URL: https://github.com/Shinnoyaninsha/desktoppython/archive/refs/tags/v_01.tar.gz
Author: anthonyredgrave24
Author-email: anthonyhamann24@gmail.com
License: MIT
Keywords: Python,Data,Analysis
Classifier: Development Status :: 3 - Alpha
Classifier: Intended Audience :: Developers
Classifier: Topic :: Software Development :: Build Tools
Classifier: License :: OSI Approved :: MIT License
Classifier: Programming Language :: Python :: 3
Classifier: Programming Language :: Python :: 3.4
Classifier: Programming Language :: Python :: 3.5
Classifier: Programming Language :: Python :: 3.6
License-File: LICENSE.txt
